imops.libs/libgomp-65f46eca.so.1.0.0
imops/morphology.py
imops/utils.py
imops/__version__.py
imops/measure.py
imops/pad.py
imops/interp2d.py
imops/__init__.py
imops/box.py
imops/_configs.py
imops/radon.py
imops/interp1d.py
imops/numeric.py
imops/crop.py
imops/compat.py
imops/testing.py
imops/backend.py
imops/_build_utils.py
imops/zoom.py
imops/py.typed
imops/src/_fast_convex_hull.c
imops/src/_fast_convex_hull.cpython-311-i386-linux-gnu.so
imops/src/_fast_radon.cpython-311-i386-linux-gnu.so
imops/src/_fast_zoom.cpython-311-i386-linux-gnu.so
imops/src/_fast_measure.cpython-311-i386-linux-gnu.so
imops/src/_convex_hull.cpython-311-i386-linux-gnu.so
imops/src/_backprojection.cpython-311-i386-linux-gnu.so
imops/src/_zoom.cpython-311-i386-linux-gnu.so
imops/src/_fast_backprojection.c
imops/src/_fast_numeric.cpython-311-i386-linux-gnu.so
imops/src/_fast_backprojection.cpython-311-i386-linux-gnu.so
imops/src/_backprojection.c
imops/src/_convex_hull.c
imops/src/_fast_morphology.cpython-311-i386-linux-gnu.so
imops/src/_numba_zoom.py
imops/src/_radon.cpython-311-i386-linux-gnu.so
imops/src/_utils.cpp
imops/src/__init__.py
imops/src/_numeric.c
imops/src/_measure.cpython-311-i386-linux-gnu.so
imops/src/_radon.c
imops/src/_utils.cpython-311-i386-linux-gnu.so
imops/src/_measure.c
imops/src/_fast_morphology.c
imops/src/_fast_measure.c
imops/src/_numeric.cpython-311-i386-linux-gnu.so
imops/src/_fast_zoom.c
imops/src/_zoom.c
imops/src/_fast_numeric.c
imops/src/_morphology.cpython-311-i386-linux-gnu.so
imops/src/_morphology.c
imops/src/_fast_radon.c
imops/cpp/main.cpp
imops/cpp/cpp_modules.cpython-311-i386-linux-gnu.so
imops/cpp/interp2d/utils.h
imops/cpp/interp2d/interpolator.h
imops/cpp/interp2d/triangulator.h
imops/cpp/interp2d/delaunator/delaunator-header-only.hpp
imops/cpp/interp2d/delaunator/delaunator.cpp
imops/cpp/interp2d/delaunator/delaunator.hpp
imops-0.9.1.dist-info/top_level.txt
imops-0.9.1.dist-info/RECORD
imops-0.9.1.dist-info/LICENSE
imops-0.9.1.dist-info/METADATA
imops-0.9.1.dist-info/WHEEL
