Metadata-Version: 2.1
Name: imops
Version: 0.9.1
Summary: Efficient parallelizable algorithms for multidimensional arrays to speed up your data pipelines
Home-page: https://github.com/neuro-ml/imops
Download-URL: https://github.com/neuro-ml/imops/archive/v0.9.1.tar.gz
Author: maxme1, vovaf709, talgat, alexeybelkov
Author-email: maxme1 <max@aumi.ai>, vovaf709 <vovaf709@yandex.ru>, talgat <saparov2130@gmail.com>, alexeybelkov <fpmbelkov@gmail.com>
License: MIT License
Project-URL: Homepage, https://github.com/neuro-ml/imops
Project-URL: Issues, https://github.com/neuro-ml/imops/issues
Project-URL: Source, https://github.com/neuro-ml/imops
Project-URL: Docs, https://neuro-ml.github.io/imops
Keywords: image processing,fast,ndarray,data pipelines
Classifier: Development Status :: 5 - Production/Stable
Classifier: License :: OSI Approved :: MIT License
Classifier: Programming Language :: Python :: 3.7
Classifier: Programming Language :: Python :: 3.8
Classifier: Programming Language :: Python :: 3.9
Classifier: Programming Language :: Python :: 3.10
Classifier: Programming Language :: Python :: 3.11
Classifier: Programming Language :: Python :: 3.12
Requires-Python: >=3.7
License-File: LICENSE
Requires-Dist: scipy <2.0.0,>=1.0
Requires-Dist: scikit-image
Requires-Dist: connected-components-3d
Requires-Dist: fastremap
Requires-Dist: edt <3.0.0,>=2.0.0
Requires-Dist: dataclasses ; python_version < "3.7"
Requires-Dist: numpy <2.0.0,>=1.7 ; python_version < "3.8"
Requires-Dist: numpy <3.0.0,>=1.22 ; python_version >= "3.8"
Provides-Extra: all
Requires-Dist: numba ; extra == 'all'
Provides-Extra: numba
Requires-Dist: numba ; extra == 'numba'
